LICENSE
MANIFEST.in
README.md
setup.py
pytspsolver/__init__.py
pytspsolver.egg-info/PKG-INFO
pytspsolver.egg-info/SOURCES.txt
pytspsolver.egg-info/dependency_links.txt
pytspsolver.egg-info/requires.txt
pytspsolver.egg-info/top_level.txt
pytspsolver/entities/TSProblem.py
pytspsolver/entities/__init__.py
pytspsolver/experiments/Experiment.py
pytspsolver/experiments/__init__.py
pytspsolver/solvers/ExhaustiveSearch.py
pytspsolver/solvers/GeneticAlgorithm.py
pytspsolver/solvers/GreedySearch.py
pytspsolver/solvers/SolverBase.py
pytspsolver/solvers/__init__.py
pytspsolver/utilities/Visualizer.py
pytspsolver/utilities/__init__.py
pytspsolver/utilities/gen_experiments.py