Metadata-Version: 2.1
Name: pytspsolver
Version: 0.0.1
Summary: Easy to use python package for rapid experimentation on the classic travelling salesman problem.
Home-page: https://github.com/rithinch/pytspsolver
Author: Rithin Chalumuri
License: MIT
Keywords: tsp,optimization-experiments,python
Platform: UNKNOWN
Requires-Python: >=3.6.0
